rasb/__init__.py
rasb.py-0.0.2.dist-info/LICENSE
rasb.py-0.0.2.dist-info/METADATA
rasb.py-0.0.2.dist-info/WHEEL
rasb.py-0.0.2.dist-info/top_level.txt
rasb.py-0.0.2.dist-info/RECORD
