Metadata-Version: 2.1
Name: rasb.py
Version: 0.0.2
Summary: A small example package
Home-page: https://github.com/AstroMulti/RASB-Python-API
Author: M_ultii
Author-email: multiidev@gmail.com
License: UNKNOWN
Platform: UNKNOWN
Classifier: Programming Language :: Python :: 3
Classifier: License :: OSI Approved :: MIT License
Classifier: Operating System :: OS Independent
Requires-Python: >=3.6
